setup.py
sumit/__init__.py
sumit.egg-info/PKG-INFO
sumit.egg-info/SOURCES.txt
sumit.egg-info/dependency_links.txt
sumit.egg-info/not-zip-safe
sumit.egg-info/top_level.txt